kiarina/lib/google/cloud_storage/__init__.py
kiarina/lib/google/cloud_storage/_settings.py
kiarina/lib/google/cloud_storage/py.typed
kiarina/lib/google/cloud_storage/_helpers/__init__.py
kiarina/lib/google/cloud_storage/_helpers/get_blob.py
kiarina/lib/google/cloud_storage/_helpers/get_bucket.py
kiarina/lib/google/cloud_storage/_helpers/get_storage_client.py
kiarina_lib_google_cloud_storage-1.35.0.dist-info/METADATA
kiarina_lib_google_cloud_storage-1.35.0.dist-info/WHEEL
kiarina_lib_google_cloud_storage-1.35.0.dist-info/RECORD
